better_optimize/__init__.py
better_optimize/_version.py
better_optimize/basinhopping.py
better_optimize/constants.py
better_optimize/minimize.py
better_optimize/root.py
better_optimize/utilities.py
better_optimize/wrapper.py
better_optimize-0.2.0.dist-info/licenses/LICENSE
better_optimize-0.2.0.dist-info/METADATA
better_optimize-0.2.0.dist-info/WHEEL
better_optimize-0.2.0.dist-info/top_level.txt
better_optimize-0.2.0.dist-info/RECORD
