Metadata-Version: 2.4
Name: better_optimize
Version: 0.2.0
Summary: A drop-in replacement for scipy optimize functions with quality of life improvements
License: MIT License
Project-URL: Homepage, https://github.com/jessegrabowski/better_optimize
Project-URL: Repository, https://github.com/jessegrabowski/better_optimize.git
Project-URL: Issues, https://github.com/jessegrabowski/better_optimize/issues
Classifier: Development Status :: 4 - Beta
Classifier: Intended Audience :: Science/Research
Classifier: License :: OSI Approved :: MIT License
Classifier: Programming Language :: Python :: 3.10
Classifier: Programming Language :: Python :: 3.11
Classifier: Programming Language :: Python :: 3.12
Classifier: Programming Language :: Python :: 3.13
Classifier: Topic :: Scientific/Engineering
Classifier: Topic :: Scientific/Engineering :: Mathematics
Requires-Python: >=3.10
License-File: LICENSE
Requires-Dist: numpy
Requires-Dist: scipy>=1.15
Requires-Dist: rich
Provides-Extra: tests
Requires-Dist: pytest; extra == "tests"
Requires-Dist: pytest-cov; extra == "tests"
Requires-Dist: pre-commit; extra == "tests"
Dynamic: license-file
